LICENSE.md
MANIFEST.in
README.rst
setup.py
ovp_organizations/.gitignore
ovp_organizations/__init__.py
ovp_organizations/admin.py
ovp_organizations/apps.py
ovp_organizations/decorators.py
ovp_organizations/emails.py
ovp_organizations/models.py
ovp_organizations/permissions.py
ovp_organizations/serializers.py
ovp_organizations/urls.py
ovp_organizations/validators.py
ovp_organizations/views.py
ovp_organizations.egg-info/PKG-INFO
ovp_organizations.egg-info/SOURCES.txt
ovp_organizations.egg-info/dependency_links.txt
ovp_organizations.egg-info/not-zip-safe
ovp_organizations.egg-info/requires.txt
ovp_organizations.egg-info/top_level.txt
ovp_organizations/__pycache__/__init__.cpython-35.pyc
ovp_organizations/__pycache__/admin.cpython-35.pyc
ovp_organizations/__pycache__/apps.cpython-35.pyc
ovp_organizations/__pycache__/decorators.cpython-35.pyc
ovp_organizations/__pycache__/emails.cpython-35.pyc
ovp_organizations/__pycache__/models.cpython-35.pyc
ovp_organizations/__pycache__/permissions.cpython-35.pyc
ovp_organizations/__pycache__/serializers.cpython-35.pyc
ovp_organizations/__pycache__/urls.cpython-35.pyc
ovp_organizations/__pycache__/validators.cpython-35.pyc
ovp_organizations/__pycache__/views.cpython-35.pyc
ovp_organizations/locale/pt_BR/LC_MESSAGES/django.mo
ovp_organizations/locale/pt_BR/LC_MESSAGES/django.po
ovp_organizations/migrations/0001_initial.py
ovp_organizations/migrations/0002_organization.py
ovp_organizations/migrations/0003_organization_type.py
ovp_organizations/migrations/0004_organization_causes.py
ovp_organizations/migrations/0005_auto_20161206_1515.py
ovp_organizations/migrations/0006_auto_20161206_1612.py
ovp_organizations/migrations/0007_organization_members.py
ovp_organizations/migrations/0008_auto_20161207_1941.py
ovp_organizations/migrations/0009_organizationinvite.py
ovp_organizations/migrations/0010_auto_20161208_1619.py
ovp_organizations/migrations/0011_organization_cover.py
ovp_organizations/migrations/0012_auto_20170109_1332.py
ovp_organizations/migrations/0013_auto_20170111_1633.py
ovp_organizations/migrations/0013_auto_20170112_1417.py
ovp_organizations/migrations/0014_auto_20170112_1717.py
ovp_organizations/migrations/0015_merge_20170112_2144.py
