Metadata-Version: 1.1
Name: ovp-organizations
Version: 1.0.13
Summary: This module has core functionality for ovp organization, such as: creating, listing, editing and retrieving.
Home-page: https://github.com/OpenVolunteeringPlatform/django-ovp-organizations
Author: Atados
Author-email: arroyo@atados.com.br
License: AGPL
Download-URL: https://github.com/OpenVolunteeringPlatform/django-ovp-organizations/tarball/1.0.13
Platform: UNKNOWN
